uproxier/__init__.py
uproxier/__main__.py
uproxier/action_processors.py
uproxier/certificate_manager.py
uproxier/cli.py
uproxier/config_validator.py
uproxier/exceptions.py
uproxier/global_variables.py
uproxier/proxy_server.py
uproxier/rules_engine.py
uproxier/version.py
uproxier/web_interface.py
uproxier/examples/01_set_header.yaml
uproxier/examples/02_remove_header.yaml
uproxier/examples/03_rewrite_url.yaml
uproxier/examples/04_set_query_param.yaml
uproxier/examples/05_set_body_param.yaml
uproxier/examples/06_replace_body.yaml
uproxier/examples/07_replace_body_json.yaml
uproxier/examples/08_mock_response.yaml
uproxier/examples/09_delay.yaml
uproxier/examples/10_conditional.yaml
uproxier/examples/11_short_circuit.yaml
uproxier/examples/12_match_conditions.yaml
uproxier/examples/13_priority_stop_after_match.yaml
uproxier/examples/14_complex_workflows.yaml
uproxier/examples/15_global_variables.yaml
uproxier/examples/16_global_variables_complete.yaml
uproxier/examples/17_remove_json_field.yaml
uproxier/examples/README.md
uproxier/examples/__init__.py
uproxier/examples/config_examples.yaml
uproxier/templates/__init__.py
uproxier/templates/index.html
uproxier/templates/static/__init__.py
uproxier/templates/static/css/__init__.py
uproxier/templates/static/css/bootstrap.min.css
uproxier/templates/static/js/__init__.py
uproxier/templates/static/js/bootstrap.bundle.min.js
uproxier/templates/static/js/qrcode.min.js
uproxier/utils/__init__.py
uproxier/utils/http.py
uproxier/utils/network.py
uproxier-0.1.15.dist-info/METADATA
uproxier-0.1.15.dist-info/WHEEL
uproxier-0.1.15.dist-info/entry_points.txt
uproxier-0.1.15.dist-info/top_level.txt
uproxier-0.1.15.dist-info/RECORD
