Metadata-Version: 2.4
Name: uproxier
Version: 0.1.15
Summary: HTTP/HTTPS proxy with rules engine and web UI
Author-email: huangjincheng <hjc853@gmail.com>
License-Expression: MIT
Keywords: proxy,mitmproxy,sse,rules,mock,http,https
Classifier: Development Status :: 4 - Beta
Classifier: Intended Audience :: Developers
Classifier: Operating System :: OS Independent
Classifier: Programming Language :: Python :: 3
Classifier: Programming Language :: Python :: 3.8
Classifier: Programming Language :: Python :: 3.9
Classifier: Programming Language :: Python :: 3.10
Classifier: Programming Language :: Python :: 3.11
Classifier: Programming Language :: Python :: 3.12
Classifier: Topic :: Internet :: WWW/HTTP :: HTTP Servers
Classifier: Topic :: Software Development :: Testing
Classifier: Topic :: System :: Networking
Requires-Python: >=3.8
Requires-Dist: mitmproxy==10.2.4
Requires-Dist: flask==3.0.0
Requires-Dist: flask-cors==4.0.0
Requires-Dist: python-dotenv==1.0.0
Requires-Dist: click==8.1.7
Requires-Dist: rich==13.7.0
Requires-Dist: pyyaml==6.0.1
Requires-Dist: requests>=2.31.0
